README.md
setup.py
dujournal/__init__.py
dujournal.egg-info/PKG-INFO
dujournal.egg-info/SOURCES.txt
dujournal.egg-info/dependency_links.txt
dujournal.egg-info/requires.txt
dujournal.egg-info/top_level.txt
dujournal/jcr/__init__.py
dujournal/jcr/esi.py
dujournal/jcr/jcr.py
dujournal/jcr/jcr_api.py
dujournal/jcr/jcr_login.py
dujournal/jour/__init__.py
dujournal/jour/doi.py
dujournal/jour/letpub.py
dujournal/jour/pubmed.py
dujournal/mesh/__init__.py
dujournal/mesh/mesh.py
dujournal/parse_xml/__init__.py
dujournal/parse_xml/parse_journal.py
dujournal/parse_xml/parse_mesh.py
dujournal/schema/__init__.py
dujournal/schema/jcr.py
dujournal/schema/jouornal.py
dujournal/schema/mesh.py
dujournal/schema/sjr.py
dujournal/schema/zky.py
dujournal/sjr/__init__.py
dujournal/sjr/sjr.py
dujournal/zky/__init__.py
dujournal/zky/zky.py
dujournal/zky/zky_warn.py