Metadata-Version: 2.1
Name: dujournal
Version: 0.0.2
Summary: Some common websites related to journals, such as PubMed, JCR, ZKY, SJR
Author: DYZ
Author-email: duyuchau@gmail.com
Maintainer: DYZ
Maintainer-email: duyuchau@gmail.com
License: MIT
Platform: all
